geomodels-1.0.0.data/data/share/man/man1/geomodels-cli.1
geomodels/_ext.cpython-312-i386-linux-gnu.so
geomodels/gravity.pyx
geomodels/magnetic.pxd
geomodels/_utils.py
geomodels/_typing.py
geomodels/wmmf.py
geomodels/_ext.pyi
geomodels/geoid.pyx
geomodels/data.py
geomodels/__init__.py
geomodels/magnetic.pyx
geomodels/error.py
geomodels/cli.py
geomodels/_version.py
geomodels/gravity.pxd
geomodels/_ext.pyx
geomodels/common.pyx
geomodels/__main__.py
geomodels/geoid.pxd
geomodels/common.pxd
geomodels/tests/utils.py
geomodels/tests/test_magnetic.py
geomodels/tests/test_wmmf.py
geomodels/tests/__init__.py
geomodels/tests/test_cli.py
geomodels/tests/test_gravity.py
geomodels/tests/test_common.py
geomodels/tests/test_data.py
geomodels/tests/test_geoid.py
geomodels/tests/data/igrf12coeffs.txt
geomodels-1.0.0.dist-info/top_level.txt
geomodels-1.0.0.dist-info/RECORD
geomodels-1.0.0.dist-info/LICENSE
geomodels-1.0.0.dist-info/entry_points.txt
geomodels-1.0.0.dist-info/METADATA
geomodels-1.0.0.dist-info/WHEEL
