Metadata-Version: 2.1
Name: geomodels
Version: 1.0.0
Summary: Python package for Earth data models management
Author-email: Antonio Valentino <antonio.valentino@tiscali.it>
License: MIT License
Project-URL: Homepage, https://github.com/avalentino/geomodels
Project-URL: Documentation, https://geomodels.readthedocs.io
Project-URL: Repository, https://github.com/avalentino/geomodels.git
Project-URL: Changelog, https://github.com/avalentino/geomodels/blob/main/docs/NEWS.rst
Project-URL: Issues, https://github.com/avalentino/geomodels/issues
Keywords: geoid,gravity,magnetic
Classifier: Development Status :: 5 - Production/Stable
Classifier: Intended Audience :: Developers
Classifier: Intended Audience :: Science/Research
Classifier: License :: OSI Approved :: MIT License
Classifier: Programming Language :: Python :: 3 :: Only
Classifier: Programming Language :: Python :: 3.10
Classifier: Programming Language :: Python :: 3.11
Classifier: Programming Language :: Python :: 3.12
Classifier: Programming Language :: Python :: 3.13
Classifier: Topic :: Scientific/Engineering :: GIS
Classifier: Topic :: Software Development :: Libraries :: Python Modules
Requires-Python: >=3.10
License-File: LICENSE
Requires-Dist: numpy
Provides-Extra: cli
Requires-Dist: argcomplete; extra == "cli"
Provides-Extra: download
Requires-Dist: tqdm; extra == "download"
Provides-Extra: test
Requires-Dist: pytest; extra == "test"
Provides-Extra: all
Requires-Dist: geomodels[cli]; extra == "all"
Requires-Dist: geomodels[download]; extra == "all"
Requires-Dist: geomodels[test]; extra == "all"
